croptimizer/__init__.py
croptimizer/common.py
croptimizer/croptimizer.py
croptimizer-0.0.1.dist-info/licenses/LICENSE
croptimizer-0.0.1.dist-info/METADATA
croptimizer-0.0.1.dist-info/WHEEL
croptimizer-0.0.1.dist-info/entry_points.txt
croptimizer-0.0.1.dist-info/top_level.txt
croptimizer-0.0.1.dist-info/RECORD
